molog/__init__.py
molog/config.py
molog/handlers.py
molog-0.0.0a0.dist-info/LICENSE
molog-0.0.0a0.dist-info/METADATA
molog-0.0.0a0.dist-info/WHEEL
molog-0.0.0a0.dist-info/RECORD
