Metadata-Version: 2.1
Name: molog
Version: 0.0.0a0
Summary: logging, but more refined, typed and documented (fork of Python 1054a75)
License: MIT
Author: ilotoki0804
Author-email: ilotoki0804@gmail.com
Requires-Python: >=3.12,<4.0
Classifier: License :: OSI Approved :: MIT License
Classifier: Programming Language :: Python :: 3
Classifier: Programming Language :: Python :: 3.12
